{"file":"wire\/modules\/Process\/ProcessForgotPassword.module","textdomain":"wire--modules--process--processforgotpassword-module","translations":{"6072e83b7f35887c76e64920bd370f4a":{"text":"Obnovit heslo"},"168b9e356db803204c123e0445ef83f4":{"text":"Obnova hesla nen\u00ed povolena"},"333b348fd95607678f8a9a333cc7b7b4":{"text":"Informace o obnoven\u00ed hesla"},"a0bfb8e59e6c13fc8d990781f77694fe":{"text":"Pokra\u010dovat"},"f469dd0000597b66060ea51c52eacf58":{"text":"Va\u0161e heslo bylo \u00fasp\u011b\u0161n\u011b obnoveno. Nyn\u00ed se m\u016f\u017eete p\u0159ihl\u00e1sit."},"9ec54ec336b65da6179cf750de33ecd7":{"text":"Zapomenut\u00e9 heslo (Forgot Password)"},"3299941fe3475a594847754b9e91f3b7":{"text":"Neplatn\u00fd po\u017eadavek na zm\u011bnu hesla. V\u00e1\u0161 po\u017eadavek mohl vypr\u0161et."},"e241608b636b6cdde53b70cb2ade0daf":{"text":"Poskytuje funkci obnovy ztracen\u00e9ho hesla pro p\u0159ihla\u0161ovac\u00ed proces."},"b49caf114ce87eeb21267f29e9a62420":{"text":"Nelze dokon\u010dit obnovu hesla. Pros\u00edm, ujist\u011bte se, \u017ee jste na stejn\u00e9m po\u010d\u00edta\u010di a pou\u017e\u00edv\u00e1te stejn\u00fd web prohl\u00ed\u017ee\u010d, ze kter\u00e9ho jste odeslali po\u017eadavek."},"dcfc149491f06edb3e6942510b6fc339":{"text":"Polud m\u00e1te v na\u0161em syst\u00e9mu vytvo\u0159en \u00fa\u010det s platnou e-mail adresou, bude v\u00e1m na n\u00ed, po potvrzen\u00ed tohoto formul\u00e1\u0159e odesl\u00e1na zpr\u00e1va. Zpr\u00e1va bude obsahovat odkaz pro obnovu va\u0161eho hesla."},"6d14491a1718796766f2775f857af701":{"text":"Pro dokon\u010den\u00ed obnovy va\u0161eho hesla, klikn\u011bte na adresu n\u00ed\u017ee (nebo ji vlo\u017ete do web prohl\u00ed\u017ee\u010de) a postupujte podle instrukc\u00ed:"},"20a05da67e6b4eedd01409fb5ca365e7":{"text":"Tato URL adresa p\u0159estane b\u00fdt platn\u00e1 po 60 minut\u00e1ch od odesl\u00e1n\u00ed. Adresa mus\u00ed b\u00fdt otev\u0159ena ze stejn\u00e9ho po\u010d\u00edta\u010de a web prohl\u00ed\u017ee\u010de jako byl odesl\u00e1n po\u017eadavek na obnovu hesla."},"edcc4a7ecb7854d0ea84fff05b5eeb3e":{"text":"Pokud byly nalezeny informace o va\u0161em u\u017eivatelsk\u00e9m \u00fa\u010dtu s platnou e-mailovou adresou. Byl odesl\u00e1n e-mail s informacemi pro obnovu hesla."},"43da6233b07fcc59791c3f91861ab7b5":{"text":"Pros\u00edm zkontrolujte si va\u0161\u00ed e-mailovou schr\u00e1nku. Pokud neobdr\u017e\u00edte do 15 minut zpr\u00e1vu, kontaktujte spr\u00e1vce pro obnovu hesla. Tento po\u017eadavek vypr\u0161\u00ed do 60 minut. Dokud nedokon\u010d\u00edte proces obnovy hesla, nezav\u00edrejte toto okno."},"5b69044da7774b93059c878056e1c28a":{"text":"Zadejte va\u0161e u\u017eivatelsk\u00e9 jm\u00e9no"}}}